azureml/__init__.py
azureml/_third_party_notice/NOTICE.txt
azureml/synapse/__init__.py
azureml/synapse/_version.py
azureml/synapse/consts.py
azureml/synapse/sessiontracker.py
azureml/synapse/synapsecomm.py
azureml/synapse/synapseerrordetails.py
azureml/synapse/synapseerrorparser.py
azureml/synapse/synapselivyreliablehttpclient.py
azureml/synapse/synapsesession.py
azureml/synapse/telemetryutils.py
azureml/synapse/utils.py
azureml/synapse/magics/__init__.py
azureml/synapse/magics/remotesynapsemagics.py
azureml/synapse/magics/synapsemagicsbase.py
azureml/synapse/magics/_ipython_config/ipython_config.py
azureml_synapse-1.60.0.data/data/etc/ipython/ipython_config.py
azureml_synapse-1.60.0.data/data/etc/jupyter/nbconfig/notebook.d/azureml_synapse.json
azureml_synapse-1.60.0.data/data/share/jupyter/lab/extensions/azureml_synapse_jupyterlab-1.5.0.tgz
azureml_synapse-1.60.0.data/data/share/jupyter/lab/settings/overrides.json
azureml_synapse-1.60.0.data/data/share/jupyter/nbextensions/azureml_synapse/8a7630caadfb15dbd13cb469853ab004.gif
azureml_synapse-1.60.0.data/data/share/jupyter/nbextensions/azureml_synapse/module.js
azureml_synapse-1.60.0.data/data/share/jupyter/nbextensions/azureml_synapse/module.js.map
azureml_synapse-1.60.0.data/data/share/jupyter/nbextensions/azureml_synapse/taskchart.js
azureml_synapse-1.60.0.data/data/share/jupyter/nbextensions/azureml_synapse/taskchart.js.map
azureml_synapse-1.60.0.data/data/share/jupyter/nbextensions/azureml_synapse/timeline.js
azureml_synapse-1.60.0.data/data/share/jupyter/nbextensions/azureml_synapse/timeline.js.map
azureml_synapse-1.60.0.dist-info/licenses/LICENSE.txt
azureml_synapse-1.60.0.dist-info/METADATA
azureml_synapse-1.60.0.dist-info/WHEEL
azureml_synapse-1.60.0.dist-info/top_level.txt
azureml_synapse-1.60.0.dist-info/RECORD
